install.py
main.py
split_speakers.py
speaker_diarization_system-1.0.2.dist-info/licenses/LICENSE
speaker_diarization_system-1.0.2.dist-info/METADATA
speaker_diarization_system-1.0.2.dist-info/WHEEL
speaker_diarization_system-1.0.2.dist-info/entry_points.txt
speaker_diarization_system-1.0.2.dist-info/top_level.txt
speaker_diarization_system-1.0.2.dist-info/RECORD
