Metadata-Version: 2.4
Name: speaker-diarization-system
Version: 1.0.2
Summary: An AI-powered script to identify speakers in an audio file and split them into separate, clean tracks.
Author-email: Lukium <lukium@pm.me>
License: MIT License
Project-URL: Homepage, https://github.com/lukium/speaker-diarization-system
Project-URL: Bug Tracker, https://github.com/lukium/speaker-diarization-system/issues
Keywords: diarization,speaker,audio,pyannote,splitter,ai
Requires-Python: >=3.11
License-File: LICENSE
Requires-Dist: pyannote.audio
Requires-Dist: pyannote.core
Requires-Dist: pyannote.database
Requires-Dist: pyannote.metrics
Requires-Dist: pyannote.pipeline
Requires-Dist: pytorch-lightning
Requires-Dist: torchmetrics
Requires-Dist: numpy>=2.0
Requires-Dist: python-dotenv
Requires-Dist: huggingface_hub
Requires-Dist: pydub
Dynamic: license-file
